ppdb_auth_lib/__init__.py
ppdb_auth_lib/auth.py
ppdb_auth_lib/percobaan.py
ppdb_auth_lib-0.2.2.dist-info/METADATA
ppdb_auth_lib-0.2.2.dist-info/WHEEL
ppdb_auth_lib-0.2.2.dist-info/top_level.txt
ppdb_auth_lib-0.2.2.dist-info/RECORD
