Metadata-Version: 2.1
Name: ppdb-auth-lib
Version: 0.2.2
Summary: Auth Library PPDBV2
Author: mrizkyff
License: MIT
Requires-Dist: pyjwt
